markdown_to_data/__init__.py
markdown_to_data/markdown_to_data.py
markdown_to_data/py.typed
markdown_to_data/to_md/md_elements_list.py
markdown_to_data/to_md/to_md_parser.py
markdown_to_data/to_md/md_elements/to_md_blockquotes.py
markdown_to_data/to_md/md_elements/to_md_code.py
markdown_to_data/to_md/md_elements/to_md_def_lists.py
markdown_to_data/to_md/md_elements/to_md_headers.py
markdown_to_data/to_md/md_elements/to_md_lists.py
markdown_to_data/to_md/md_elements/to_md_metadata.py
markdown_to_data/to_md/md_elements/to_md_paragraphs.py
markdown_to_data/to_md/md_elements/to_md_separator.py
markdown_to_data/to_md/md_elements/to_md_tables.py
markdown_to_data/to_python/to_python_objects.py
markdown_to_data/to_python/classification/classification.py
markdown_to_data/to_python/classification/line_content_classification.py
markdown_to_data/to_python/classification/md_classification/classify_md_blockquote.py
markdown_to_data/to_python/classification/md_classification/classify_md_code.py
markdown_to_data/to_python/classification/md_classification/classify_md_definition_list.py
markdown_to_data/to_python/classification/md_classification/classify_md_header.py
markdown_to_data/to_python/classification/md_classification/classify_md_list.py
markdown_to_data/to_python/classification/md_classification/classify_md_metadata.py
markdown_to_data/to_python/classification/md_classification/classify_md_paragraph.py
markdown_to_data/to_python/classification/md_classification/classify_md_separator.py
markdown_to_data/to_python/classification/md_classification/classify_md_table_row.py
markdown_to_data/to_python/convert_single_line_objects/convert_headers.py
markdown_to_data/to_python/convert_single_line_objects/convert_paragraphs.py
markdown_to_data/to_python/convert_single_line_objects/convert_separators.py
markdown_to_data/to_python/hierarchy/hierarchy.py
markdown_to_data/to_python/merging_multiline_objects/line_utils.py
markdown_to_data-2.0.1.dist-info/METADATA
markdown_to_data-2.0.1.dist-info/WHEEL
markdown_to_data-2.0.1.dist-info/licenses/LICENSE
markdown_to_data-2.0.1.dist-info/RECORD
