Metadata-Version: 2.4
Name: markdown-to-data
Version: 2.0.1
Summary: Convert markdown and its elements (tables, lists, code, etc.) into structured, easily processable data formats like lists and hierarchical dictionaries (or JSON), with support for parsing back to markdown.
Project-URL: Homepage, https://github.com/lennartpollvogt/markdown-to-data
Project-URL: Repository, https://github.com/lennartpollvogt/markdown-to-data
Author-email: Lennart Pollvogt <lennartpollvogt@protonmail.com>
License-Expression: MIT
License-File: LICENSE
Keywords: json,lists,markdown,markdown-parser,markdown-to-data,markdown-to-json,md,parser,parsing,tables
Classifier: Intended Audience :: Developers
Classifier: License :: OSI Approved :: MIT License
Classifier: Operating System :: OS Independent
Classifier: Programming Language :: Python
Classifier: Programming Language :: Python :: 3
Classifier: Topic :: Software Development :: Libraries :: Python Modules
Classifier: Topic :: Text Processing :: Markup :: Markdown
Requires-Python: >=3.10
Requires-Dist: tomli>=1.2.0; python_version < '3.11'
